[
  {
    "name": "Temperature",
    "dataType": "float",
    "description": "Records the temperature."
  },
  {
    "name": "Humidity",
    "dataType": "float",
    "description": "Records the humidity level."
  },
  {
    "name": "Pressure",
    "dataType": "int",
    "description": "Records the pressure level."
  },
  {
    "name": "Altitude",
    "dataType": "float",
    "description": "Records the altitude."
  },
  {
    "name": "Number of Estimators",
    "dataType": "int",
    "description": "Number of Trees in Random Forest."
  },
  {
    "name": "Criterion",
    "dataType": "text",
    "description": "The function to measure the quality of a split."
  }
]
